{
    "total": [
        {
            "id": "100057835395048",
            "count": 0
        },
        {
            "id": "100077962617953",
            "count": 0
        },
        {
            "id": "100075549183492",
            "count": 0
        },
        {
            "id": "100083437479332",
            "count": 0
        },
        {
            "id": "100072262945505",
            "count": 0
        },
        {
            "id": "100081933152243",
            "count": 0
        },
        {
            "id": "100057255793821",
            "count": 0
        },
        {
            "id": "100061160525111",
            "count": 0
        },
        {
            "id": "100003464693338",
            "count": 0
        },
        {
            "id": "100043432521009",
            "count": 0
        },
        {
            "id": "100043058417559",
            "count": 0
        },
        {
            "id": "100049160025223",
            "count": 0
        },
        {
            "id": "100071731943609",
            "count": 0
        },
        {
            "id": "100048497987037",
            "count": 0
        },
        {
            "id": "100076458470224",
            "count": 0
        },
        {
            "id": "100002360645889",
            "count": 0
        },
        {
            "id": "100018903488678",
            "count": 0
        },
        {
            "id": "100022730772020",
            "count": 4
        },
        {
            "id": "61551713953434",
            "count": 0
        },
        {
            "id": "100024578092475",
            "count": 0
        },
        {
            "id": "100087603810337",
            "count": 0
        },
        {
            "id": "100018423642261",
            "count": 1
        },
        {
            "id": "100069480398073",
            "count": 0
        },
        {
            "id": "100028369471910",
            "count": 0
        },
        {
            "id": "100084867652332",
            "count": 3
        },
        {
            "id": "100058975853837",
            "count": 0
        },
        {
            "id": "100036432797833",
            "count": 0
        },
        {
            "id": "100078455981875",
            "count": 0
        },
        {
            "id": "100076359056607",
            "count": 2
        },
        {
            "id": "100013954718432",
            "count": 0
        },
        {
            "id": "100091848575177",
            "count": 0
        },
        {
            "id": "100049381070901",
            "count": 0
        },
        {
            "id": "100028810485891",
            "count": 0
        },
        {
            "id": "100056115038181",
            "count": 0
        },
        {
            "id": "100058513397787",
            "count": 0
        },
        {
            "id": "100024257358584",
            "count": 0
        },
        {
            "id": "100051341473114",
            "count": 0
        },
        {
            "id": "100082035912224",
            "count": 0
        },
        {
            "id": "61551930862917",
            "count": 1
        },
        {
            "id": "100075074096133",
            "count": 0
        },
        {
            "id": "100079313787186",
            "count": 0
        },
        {
            "id": "100021903122785",
            "count": 0
        },
        {
            "id": "100014491754063",
            "count": 0
        },
        {
            "id": "100044813057296",
            "count": 0
        },
        {
            "id": "100005432957505",
            "count": 0
        },
        {
            "id": "100007096786614",
            "count": 0
        },
        {
            "id": "100054392607204",
            "count": 0
        },
        {
            "id": "593577006",
            "count": 3
        },
        {
            "id": "100036848532913",
            "count": 0
        },
        {
            "id": "100090522225633",
            "count": 0
        },
        {
            "id": "100058104136285",
            "count": 0
        },
        {
            "id": "100041071098147",
            "count": 0
        },
        {
            "id": "100044749682853",
            "count": 0
        },
        {
            "id": "100083552148604",
            "count": 0
        },
        {
            "id": "100095709811168",
            "count": 0
        },
        {
            "id": "100080936564253",
            "count": 0
        },
        {
            "id": "100022334179916",
            "count": 0
        },
        {
            "id": "100057189174758",
            "count": 0
        },
        {
            "id": "100083100676823",
            "count": 0
        },
        {
            "id": "100093293222130",
            "count": 0
        },
        {
            "id": "100090914633560",
            "count": 0
        },
        {
            "id": "100006870976840",
            "count": 0
        },
        {
            "id": "100014962573966",
            "count": 0
        },
        {
            "id": "100054608116445",
            "count": 0
        },
        {
            "id": "100081137642852",
            "count": 3
        },
        {
            "id": "100033496605927",
            "count": 0
        },
        {
            "id": "100080813023081",
            "count": 0
        }
    ],
    "week": [
        {
            "id": "100057835395048",
            "count": 0,
            "name": "Lê Tố Nhi"
        },
        {
            "id": "100077962617953",
            "count": 0,
            "name": "Trà My"
        },
        {
            "id": "100075549183492",
            "count": 0,
            "name": "Nguyễn Thành Nam"
        },
        {
            "id": "100083437479332",
            "count": 0,
            "name": "Khoii Le"
        },
        {
            "id": "100072262945505",
            "count": 0,
            "name": "Astrea Reinhard"
        },
        {
            "id": "100081933152243",
            "count": 0,
            "name": "Hưng Nguyễn"
        },
        {
            "id": "100057255793821",
            "count": 0,
            "name": "Trường Hưng"
        },
        {
            "id": "100061160525111",
            "count": 0,
            "name": "Cường Thịnh ☁️"
        },
        {
            "id": "100003464693338",
            "count": 0,
            "name": "Cường Thịnh"
        },
        {
            "id": "100043432521009",
            "count": 0,
            "name": "Hồ Trà My"
        },
        {
            "id": "100043058417559",
            "count": 0,
            "name": "Phạm Nguyệt"
        },
        {
            "id": "100049160025223",
            "count": 0,
            "name": "Diễm Thi Mai Mai"
        },
        {
            "id": "100071731943609",
            "count": 0,
            "name": "Nguyễn Cường Thịnh✅"
        },
        {
            "id": "100048497987037",
            "count": 0,
            "name": "Thy Ngọc Nguyễn"
        },
        {
            "id": "100076458470224",
            "count": 0,
            "name": "Tuấn Trần"
        },
        {
            "id": "100002360645889",
            "count": 0,
            "name": "Đình Đạt"
        },
        {
            "id": "100018903488678",
            "count": 0,
            "name": "Phạm Hải Luân"
        },
        {
            "id": "100022730772020",
            "count": 0,
            "name": "Khánnh Linnh"
        },
        {
            "id": "61551713953434",
            "count": 0,
            "name": "Huy Anh"
        },
        {
            "id": "100024578092475",
            "count": 0,
            "name": "Tr Thu Nguyệt"
        },
        {
            "id": "100087603810337",
            "count": 0,
            "name": "Trần Ngọc Khánh Linh"
        },
        {
            "id": "100018423642261",
            "count": 0,
            "name": "Kiều Chinh"
        },
        {
            "id": "100069480398073",
            "count": 0,
            "name": "Hoang Thi Duyen"
        },
        {
            "id": "100028369471910",
            "count": 0,
            "name": "Gia Huy"
        },
        {
            "id": "100084867652332",
            "count": 0,
            "name": "Bùi Đình Duy Anh"
        },
        {
            "id": "100058975853837",
            "count": 0,
            "name": "Tấn Thịnh"
        },
        {
            "id": "100036432797833",
            "count": 0,
            "name": "Vũ Thanh Tùng"
        },
        {
            "id": "100078455981875",
            "count": 0,
            "name": "Đinh Ngọc Ánh"
        },
        {
            "id": "100076359056607",
            "count": 0,
            "name": "Truc Anh"
        },
        {
            "id": "100013954718432",
            "count": 0,
            "name": "Phương Uyên"
        },
        {
            "id": "100091848575177",
            "count": 0,
            "name": "Nọc Én"
        },
        {
            "id": "100049381070901",
            "count": 0,
            "name": "Viết Mân"
        },
        {
            "id": "100028810485891",
            "count": 0,
            "name": "Đoàn Mạnh Hiếu"
        },
        {
            "id": "100056115038181",
            "count": 0,
            "name": "Lưu Quốc Hợp"
        },
        {
            "id": "100058513397787",
            "count": 0,
            "name": "Vũ Khắc Lục"
        },
        {
            "id": "100024257358584",
            "count": 0,
            "name": "Đình Khoa"
        },
        {
            "id": "100051341473114",
            "count": 0,
            "name": "Hồng Ngân"
        },
        {
            "id": "100082035912224",
            "count": 0,
            "name": "Nguyễn Nguyên"
        },
        {
            "id": "61551930862917",
            "count": 0,
            "name": "Nam Hoàng"
        },
        {
            "id": "100075074096133",
            "count": 0,
            "name": "Sane Sane"
        },
        {
            "id": "100079313787186",
            "count": 0,
            "name": "Trần Thắng"
        },
        {
            "id": "100021903122785",
            "count": 0,
            "name": "함지민"
        },
        {
            "id": "100014491754063",
            "count": 0,
            "name": "Nguyễn Đình Anh Tài"
        },
        {
            "id": "100044813057296",
            "count": 0,
            "name": "Đức Khương"
        },
        {
            "id": "100005432957505",
            "count": 0,
            "name": "Bảo Phúc"
        },
        {
            "id": "100007096786614",
            "count": 0,
            "name": "Nguyen Kien"
        },
        {
            "id": "100054392607204",
            "count": 0,
            "name": "Thang Nguyen"
        },
        {
            "id": "593577006",
            "count": 0,
            "name": "Ngô Trung Kiên"
        },
        {
            "id": "100036848532913",
            "count": 0,
            "name": "Bảo Nam"
        },
        {
            "id": "100090522225633",
            "count": 0,
            "name": "Ngọc Linh"
        },
        {
            "id": "100058104136285",
            "count": 0,
            "name": "Nguyễn Minh Tùng"
        },
        {
            "id": "100041071098147",
            "count": 0,
            "name": "Hoàng Tú"
        },
        {
            "id": "100044749682853",
            "count": 0,
            "name": "Đào Ngọc Bích"
        },
        {
            "id": "100083552148604",
            "count": 0,
            "name": "Nguyễn Thế Chiến"
        },
        {
            "id": "100095709811168",
            "count": 0,
            "name": "Nguyễn Duy"
        },
        {
            "id": "100080936564253",
            "count": 0,
            "name": "Mary Lin"
        },
        {
            "id": "100022334179916",
            "count": 0,
            "name": "Tường Vy"
        },
        {
            "id": "100057189174758",
            "count": 0,
            "name": "Hoàng Bảo Khanh"
        },
        {
            "id": "100083100676823",
            "count": 0,
            "name": "Minh Duc"
        },
        {
            "id": "100093293222130",
            "count": 0,
            "name": "Tiến Giang😏✅👾"
        },
        {
            "id": "100090914633560",
            "count": 0,
            "name": "Nguyễn Khánh Duy"
        },
        {
            "id": "100006870976840",
            "count": 0,
            "name": "Trung Sơn"
        },
        {
            "id": "100014962573966",
            "count": 0,
            "name": "Bảo Trân"
        },
        {
            "id": "100054608116445",
            "count": 0,
            "name": "Đức Duy"
        },
        {
            "id": "100081137642852",
            "count": 0,
            "name": "Đăng Khôi"
        },
        {
            "id": "100033496605927",
            "count": 0,
            "name": "Nguyen NamHung"
        },
        {
            "id": "100080813023081",
            "count": 0,
            "name": "Tâm Nguyễn"
        }
    ],
    "day": [
        {
            "id": "100057835395048",
            "count": 0,
            "name": "Lê Tố Nhi"
        },
        {
            "id": "100077962617953",
            "count": 0,
            "name": "Trà My"
        },
        {
            "id": "100075549183492",
            "count": 0,
            "name": "Nguyễn Thành Nam"
        },
        {
            "id": "100083437479332",
            "count": 0,
            "name": "Khoii Le"
        },
        {
            "id": "100072262945505",
            "count": 0,
            "name": "Astrea Reinhard"
        },
        {
            "id": "100081933152243",
            "count": 0,
            "name": "Hưng Nguyễn"
        },
        {
            "id": "100057255793821",
            "count": 0,
            "name": "Trường Hưng"
        },
        {
            "id": "100061160525111",
            "count": 0,
            "name": "Cường Thịnh ☁️"
        },
        {
            "id": "100003464693338",
            "count": 0,
            "name": "Cường Thịnh"
        },
        {
            "id": "100043432521009",
            "count": 0,
            "name": "Hồ Trà My"
        },
        {
            "id": "100043058417559",
            "count": 0,
            "name": "Phạm Nguyệt"
        },
        {
            "id": "100049160025223",
            "count": 0,
            "name": "Diễm Thi Mai Mai"
        },
        {
            "id": "100071731943609",
            "count": 0,
            "name": "Nguyễn Cường Thịnh✅"
        },
        {
            "id": "100048497987037",
            "count": 0,
            "name": "Thy Ngọc Nguyễn"
        },
        {
            "id": "100076458470224",
            "count": 0,
            "name": "Tuấn Trần"
        },
        {
            "id": "100002360645889",
            "count": 0,
            "name": "Đình Đạt"
        },
        {
            "id": "100018903488678",
            "count": 0,
            "name": "Phạm Hải Luân"
        },
        {
            "id": "100022730772020",
            "count": 0,
            "name": "Khánnh Linnh"
        },
        {
            "id": "61551713953434",
            "count": 0,
            "name": "Huy Anh"
        },
        {
            "id": "100024578092475",
            "count": 0,
            "name": "Tr Thu Nguyệt"
        },
        {
            "id": "100087603810337",
            "count": 0,
            "name": "Trần Ngọc Khánh Linh"
        },
        {
            "id": "100018423642261",
            "count": 0,
            "name": "Kiều Chinh"
        },
        {
            "id": "100069480398073",
            "count": 0,
            "name": "Hoang Thi Duyen"
        },
        {
            "id": "100028369471910",
            "count": 0,
            "name": "Gia Huy"
        },
        {
            "id": "100084867652332",
            "count": 0,
            "name": "Bùi Đình Duy Anh"
        },
        {
            "id": "100058975853837",
            "count": 0,
            "name": "Tấn Thịnh"
        },
        {
            "id": "100036432797833",
            "count": 0,
            "name": "Vũ Thanh Tùng"
        },
        {
            "id": "100078455981875",
            "count": 0,
            "name": "Đinh Ngọc Ánh"
        },
        {
            "id": "100076359056607",
            "count": 0,
            "name": "Truc Anh"
        },
        {
            "id": "100013954718432",
            "count": 0,
            "name": "Phương Uyên"
        },
        {
            "id": "100091848575177",
            "count": 0,
            "name": "Nọc Én"
        },
        {
            "id": "100049381070901",
            "count": 0,
            "name": "Viết Mân"
        },
        {
            "id": "100028810485891",
            "count": 0,
            "name": "Đoàn Mạnh Hiếu"
        },
        {
            "id": "100056115038181",
            "count": 0,
            "name": "Lưu Quốc Hợp"
        },
        {
            "id": "100058513397787",
            "count": 0,
            "name": "Vũ Khắc Lục"
        },
        {
            "id": "100024257358584",
            "count": 0,
            "name": "Đình Khoa"
        },
        {
            "id": "100051341473114",
            "count": 0,
            "name": "Hồng Ngân"
        },
        {
            "id": "100082035912224",
            "count": 0,
            "name": "Nguyễn Nguyên"
        },
        {
            "id": "61551930862917",
            "count": 0,
            "name": "Nam Hoàng"
        },
        {
            "id": "100075074096133",
            "count": 0,
            "name": "Sane Sane"
        },
        {
            "id": "100079313787186",
            "count": 0,
            "name": "Trần Thắng"
        },
        {
            "id": "100021903122785",
            "count": 0,
            "name": "함지민"
        },
        {
            "id": "100014491754063",
            "count": 0,
            "name": "Nguyễn Đình Anh Tài"
        },
        {
            "id": "100044813057296",
            "count": 0,
            "name": "Đức Khương"
        },
        {
            "id": "100005432957505",
            "count": 0,
            "name": "Bảo Phúc"
        },
        {
            "id": "100007096786614",
            "count": 0,
            "name": "Nguyen Kien"
        },
        {
            "id": "100054392607204",
            "count": 0,
            "name": "Thang Nguyen"
        },
        {
            "id": "593577006",
            "count": 0,
            "name": "Ngô Trung Kiên"
        },
        {
            "id": "100036848532913",
            "count": 0,
            "name": "Bảo Nam"
        },
        {
            "id": "100090522225633",
            "count": 0,
            "name": "Ngọc Linh"
        },
        {
            "id": "100058104136285",
            "count": 0,
            "name": "Nguyễn Minh Tùng"
        },
        {
            "id": "100041071098147",
            "count": 0,
            "name": "Hoàng Tú"
        },
        {
            "id": "100044749682853",
            "count": 0,
            "name": "Đào Ngọc Bích"
        },
        {
            "id": "100083552148604",
            "count": 0,
            "name": "Nguyễn Thế Chiến"
        },
        {
            "id": "100095709811168",
            "count": 0,
            "name": "Nguyễn Duy"
        },
        {
            "id": "100080936564253",
            "count": 0,
            "name": "Mary Lin"
        },
        {
            "id": "100022334179916",
            "count": 0,
            "name": "Tường Vy"
        },
        {
            "id": "100057189174758",
            "count": 0,
            "name": "Hoàng Bảo Khanh"
        },
        {
            "id": "100083100676823",
            "count": 0,
            "name": "Minh Duc"
        },
        {
            "id": "100093293222130",
            "count": 0,
            "name": "Tiến Giang😏✅👾"
        },
        {
            "id": "100090914633560",
            "count": 0,
            "name": "Nguyễn Khánh Duy"
        },
        {
            "id": "100006870976840",
            "count": 0,
            "name": "Trung Sơn"
        },
        {
            "id": "100014962573966",
            "count": 0,
            "name": "Bảo Trân"
        },
        {
            "id": "100054608116445",
            "count": 0,
            "name": "Đức Duy"
        },
        {
            "id": "100081137642852",
            "count": 0,
            "name": "Đăng Khôi"
        },
        {
            "id": "100033496605927",
            "count": 0,
            "name": "Nguyen NamHung"
        },
        {
            "id": "100080813023081",
            "count": 0,
            "name": "Tâm Nguyễn"
        }
    ],
    "time": 3,
    "last": {
        "time": 4,
        "day": [
            {
                "id": "100057835395048",
                "count": 0
            },
            {
                "id": "100077962617953",
                "count": 0
            },
            {
                "id": "100075549183492",
                "count": 0
            },
            {
                "id": "100083437479332",
                "count": 0
            },
            {
                "id": "100072262945505",
                "count": 0
            },
            {
                "id": "100081933152243",
                "count": 0
            },
            {
                "id": "100057255793821",
                "count": 0
            },
            {
                "id": "100061160525111",
                "count": 0
            },
            {
                "id": "100003464693338",
                "count": 0
            },
            {
                "id": "100043432521009",
                "count": 0
            },
            {
                "id": "100043058417559",
                "count": 0
            },
            {
                "id": "100049160025223",
                "count": 0
            },
            {
                "id": "100071731943609",
                "count": 0
            },
            {
                "id": "100048497987037",
                "count": 0
            },
            {
                "id": "100076458470224",
                "count": 0
            },
            {
                "id": "100002360645889",
                "count": 0
            },
            {
                "id": "100018903488678",
                "count": 0
            },
            {
                "id": "100022730772020",
                "count": 0
            },
            {
                "id": "61551713953434",
                "count": 0
            },
            {
                "id": "100024578092475",
                "count": 0
            },
            {
                "id": "100087603810337",
                "count": 0
            },
            {
                "id": "100018423642261",
                "count": 0
            },
            {
                "id": "100069480398073",
                "count": 0
            },
            {
                "id": "100028369471910",
                "count": 0
            },
            {
                "id": "100084867652332",
                "count": 0
            },
            {
                "id": "100058975853837",
                "count": 0
            },
            {
                "id": "100036432797833",
                "count": 0
            },
            {
                "id": "100078455981875",
                "count": 0
            },
            {
                "id": "100076359056607",
                "count": 0
            },
            {
                "id": "100013954718432",
                "count": 0
            },
            {
                "id": "100091848575177",
                "count": 0
            },
            {
                "id": "100049381070901",
                "count": 0
            },
            {
                "id": "100028810485891",
                "count": 0
            },
            {
                "id": "100056115038181",
                "count": 0
            },
            {
                "id": "100058513397787",
                "count": 0
            },
            {
                "id": "100024257358584",
                "count": 0
            },
            {
                "id": "100051341473114",
                "count": 0
            },
            {
                "id": "100082035912224",
                "count": 0
            },
            {
                "id": "61551930862917",
                "count": 0
            },
            {
                "id": "100075074096133",
                "count": 0
            },
            {
                "id": "100079313787186",
                "count": 0
            },
            {
                "id": "100021903122785",
                "count": 0
            },
            {
                "id": "100014491754063",
                "count": 0
            },
            {
                "id": "100044813057296",
                "count": 0
            },
            {
                "id": "100005432957505",
                "count": 0
            },
            {
                "id": "100007096786614",
                "count": 0
            },
            {
                "id": "100054392607204",
                "count": 0
            },
            {
                "id": "593577006",
                "count": 0
            },
            {
                "id": "100036848532913",
                "count": 0
            },
            {
                "id": "100090522225633",
                "count": 0
            },
            {
                "id": "100058104136285",
                "count": 0
            },
            {
                "id": "100041071098147",
                "count": 0
            },
            {
                "id": "100044749682853",
                "count": 0
            },
            {
                "id": "100083552148604",
                "count": 0
            },
            {
                "id": "100095709811168",
                "count": 0
            },
            {
                "id": "100080936564253",
                "count": 0
            },
            {
                "id": "100022334179916",
                "count": 0
            },
            {
                "id": "100057189174758",
                "count": 0
            },
            {
                "id": "100083100676823",
                "count": 0
            },
            {
                "id": "100093293222130",
                "count": 0
            },
            {
                "id": "100090914633560",
                "count": 0
            },
            {
                "id": "100006870976840",
                "count": 0
            },
            {
                "id": "100014962573966",
                "count": 0
            },
            {
                "id": "100054608116445",
                "count": 0
            },
            {
                "id": "100081137642852",
                "count": 0
            },
            {
                "id": "100033496605927",
                "count": 0
            },
            {
                "id": "100080813023081",
                "count": 0
            }
        ],
        "week": [
            {
                "id": "100057835395048",
                "count": 0
            },
            {
                "id": "100077962617953",
                "count": 0
            },
            {
                "id": "100075549183492",
                "count": 0
            },
            {
                "id": "100083437479332",
                "count": 0
            },
            {
                "id": "100072262945505",
                "count": 0
            },
            {
                "id": "100081933152243",
                "count": 0
            },
            {
                "id": "100057255793821",
                "count": 0
            },
            {
                "id": "100061160525111",
                "count": 0
            },
            {
                "id": "100003464693338",
                "count": 0
            },
            {
                "id": "100043432521009",
                "count": 0
            },
            {
                "id": "100043058417559",
                "count": 0
            },
            {
                "id": "100049160025223",
                "count": 0
            },
            {
                "id": "100071731943609",
                "count": 0
            },
            {
                "id": "100048497987037",
                "count": 0
            },
            {
                "id": "100076458470224",
                "count": 0
            },
            {
                "id": "100002360645889",
                "count": 0
            },
            {
                "id": "100018903488678",
                "count": 0
            },
            {
                "id": "100022730772020",
                "count": 0
            },
            {
                "id": "61551713953434",
                "count": 0
            },
            {
                "id": "100024578092475",
                "count": 0
            },
            {
                "id": "100087603810337",
                "count": 0
            },
            {
                "id": "100018423642261",
                "count": 0
            },
            {
                "id": "100069480398073",
                "count": 0
            },
            {
                "id": "100028369471910",
                "count": 0
            },
            {
                "id": "100084867652332",
                "count": 0
            },
            {
                "id": "100058975853837",
                "count": 0
            },
            {
                "id": "100036432797833",
                "count": 0
            },
            {
                "id": "100078455981875",
                "count": 0
            },
            {
                "id": "100076359056607",
                "count": 0
            },
            {
                "id": "100013954718432",
                "count": 0
            },
            {
                "id": "100091848575177",
                "count": 0
            },
            {
                "id": "100049381070901",
                "count": 0
            },
            {
                "id": "100028810485891",
                "count": 0
            },
            {
                "id": "100056115038181",
                "count": 0
            },
            {
                "id": "100058513397787",
                "count": 0
            },
            {
                "id": "100024257358584",
                "count": 0
            },
            {
                "id": "100051341473114",
                "count": 0
            },
            {
                "id": "100082035912224",
                "count": 0
            },
            {
                "id": "61551930862917",
                "count": 0
            },
            {
                "id": "100075074096133",
                "count": 0
            },
            {
                "id": "100079313787186",
                "count": 0
            },
            {
                "id": "100021903122785",
                "count": 0
            },
            {
                "id": "100014491754063",
                "count": 0
            },
            {
                "id": "100044813057296",
                "count": 0
            },
            {
                "id": "100005432957505",
                "count": 0
            },
            {
                "id": "100007096786614",
                "count": 0
            },
            {
                "id": "100054392607204",
                "count": 0
            },
            {
                "id": "593577006",
                "count": 0
            },
            {
                "id": "100036848532913",
                "count": 0
            },
            {
                "id": "100090522225633",
                "count": 0
            },
            {
                "id": "100058104136285",
                "count": 0
            },
            {
                "id": "100041071098147",
                "count": 0
            },
            {
                "id": "100044749682853",
                "count": 0
            },
            {
                "id": "100083552148604",
                "count": 0
            },
            {
                "id": "100095709811168",
                "count": 0
            },
            {
                "id": "100080936564253",
                "count": 0
            },
            {
                "id": "100022334179916",
                "count": 0
            },
            {
                "id": "100057189174758",
                "count": 0
            },
            {
                "id": "100083100676823",
                "count": 0
            },
            {
                "id": "100093293222130",
                "count": 0
            },
            {
                "id": "100090914633560",
                "count": 0
            },
            {
                "id": "100006870976840",
                "count": 0
            },
            {
                "id": "100014962573966",
                "count": 0
            },
            {
                "id": "100054608116445",
                "count": 0
            },
            {
                "id": "100081137642852",
                "count": 0
            },
            {
                "id": "100033496605927",
                "count": 0
            },
            {
                "id": "100080813023081",
                "count": 0
            }
        ]
    }
}